mhagenta/__init__.py
mhagenta/bases/__init__.py
mhagenta/containers/__init__.py
mhagenta/containers/CONTAINER_VERSION.py
mhagenta/containers/mha-base/Dockerfile
mhagenta/containers/mha-main/Dockerfile
mhagenta/containers/mha-rabbitmq/Dockerfile
mhagenta/containers/mha-rabbitmq/rabbitmq-install.sh
mhagenta/core/__init__.py
mhagenta/core/agent_launcher.py
mhagenta/core/connection/__init__.py
mhagenta/core/connection/connector.py
mhagenta/core/connection/module_messenger.py
mhagenta/core/connection/rabbitmq_connector.py
mhagenta/core/connection/root_messenger.py
mhagenta/core/module_launcher.py
mhagenta/core/orchestrator.py
mhagenta/core/processes/__init__.py
mhagenta/core/processes/mha_module.py
mhagenta/core/processes/mha_root.py
mhagenta/core/processes/process.py
mhagenta/defaults/__init__.py
mhagenta/defaults/communication/__init__.py
mhagenta/defaults/communication/rabbitmq/__init__.py
mhagenta/defaults/communication/rabbitmq/environment.py
mhagenta/defaults/communication/rabbitmq/modules.py
mhagenta/defaults/communication/rest/__init__.py
mhagenta/defaults/communication/rest/environment.py
mhagenta/defaults/communication/rest/receiver.py
mhagenta/defaults/communication/rest/rest.py
mhagenta/environment/__init__.py
mhagenta/environment/environment.py
mhagenta/environment/environment_launcher.py
mhagenta/gui/__init__.py
mhagenta/gui/monitor.py
mhagenta/modules/__init__.py
mhagenta/modules/actuation/__init__.py
mhagenta/modules/actuation/actuator.py
mhagenta/modules/high_level/__init__.py
mhagenta/modules/high_level/goals/__init__.py
mhagenta/modules/high_level/goals/goal_graph.py
mhagenta/modules/high_level/high_level_reasoner.py
mhagenta/modules/high_level/knowledge/__init__.py
mhagenta/modules/high_level/knowledge/knowledge.py
mhagenta/modules/low_level/__init__.py
mhagenta/modules/low_level/learning/__init__.py
mhagenta/modules/low_level/learning/learner.py
mhagenta/modules/low_level/low_level_reasoner.py
mhagenta/modules/memory/__init__.py
mhagenta-1.3.8.dist-info/LICENSE
mhagenta-1.3.8.dist-info/METADATA
mhagenta-1.3.8.dist-info/WHEEL
mhagenta-1.3.8.dist-info/RECORD
