Metadata-Version: 2.1
Name: mhagenta
Version: 1.3.8
Summary: MHAgentA allows you to design and run simulations with containerized Modular Hybrid Agents.
Author: Dmitry Gnatyshak
Author-email: dmitry.gnatyshak@gmail.com
Requires-Python: >=3.12,<4.0
Classifier: Programming Language :: Python :: 3
Classifier: Programming Language :: Python :: 3.12
Requires-Dist: dill (>=0.3.9,<0.4.0)
Requires-Dist: docker (>=7.1.0,<8.0.0)
Requires-Dist: fastapi (>=0.115.5,<0.116.0)
Requires-Dist: httpx (>=0.27.2,<0.28.0)
Requires-Dist: pika (>=1.3.2,<2.0.0)
Requires-Dist: pika-stubs (>=0.1.3,<0.2.0)
Requires-Dist: pydantic (>=2.9.2,<3.0.0)
Requires-Dist: python-dateutil (>=2.9.0.post0,<3.0.0)
Requires-Dist: regex (>=2024.11.6,<2025.0.0)
